odoo/addons/l10n_es_aeat_sii_match/README.rst
odoo/addons/l10n_es_aeat_sii_match/__init__.py
odoo/addons/l10n_es_aeat_sii_match/__manifest__.py
odoo/addons/l10n_es_aeat_sii_match/i18n/es.po
odoo/addons/l10n_es_aeat_sii_match/i18n/l10n_es_aeat_sii_match.pot
odoo/addons/l10n_es_aeat_sii_match/models/__init__.py
odoo/addons/l10n_es_aeat_sii_match/models/account_move.py
odoo/addons/l10n_es_aeat_sii_match/models/aeat_sii_match_difference.py
odoo/addons/l10n_es_aeat_sii_match/models/aeat_sii_match_report.py
odoo/addons/l10n_es_aeat_sii_match/readme/CONTRIBUTORS.md
odoo/addons/l10n_es_aeat_sii_match/readme/DESCRIPTION.md
odoo/addons/l10n_es_aeat_sii_match/readme/MAINTAINERS.rst
odoo/addons/l10n_es_aeat_sii_match/security/ir.model.access.csv
odoo/addons/l10n_es_aeat_sii_match/static/description/icon.png
odoo/addons/l10n_es_aeat_sii_match/static/description/index.html
odoo/addons/l10n_es_aeat_sii_match/tests/__init__.py
odoo/addons/l10n_es_aeat_sii_match/tests/test_l10n_es_aeat_sii_match.py
odoo/addons/l10n_es_aeat_sii_match/views/account_move_views.xml
odoo/addons/l10n_es_aeat_sii_match/views/aeat_sii_match_report.xml
odoo_addon_l10n_es_aeat_sii_match-17.0.1.0.3.dist-info/METADATA
odoo_addon_l10n_es_aeat_sii_match-17.0.1.0.3.dist-info/WHEEL
odoo_addon_l10n_es_aeat_sii_match-17.0.1.0.3.dist-info/top_level.txt
odoo_addon_l10n_es_aeat_sii_match-17.0.1.0.3.dist-info/RECORD
