Metadata-Version: 2.1
Name: odoo-addon-l10n_es_aeat_sii_match
Version: 17.0.1.0.3
Requires-Python: >=3.10
Requires-Dist: deepdiff<8
Requires-Dist: odoo-addon-l10n_es_aeat_sii_oca>=17.0dev,<17.1dev
Requires-Dist: odoo>=17.0a,<17.1dev
Summary: =?utf-8?q?Sistema_de_comprobaci=C3=B3n_y_contraste_de_facturas_enviadas_al_SII?=
Home-page: https://github.com/OCA/l10n-spain
License: AGPL-3
Author: Studio73, Odoo Community Association (OCA)
Author-email: support@odoo-community.org
Classifier: Programming Language :: Python
Classifier: Framework :: Odoo
Classifier: Framework :: Odoo :: 17.0
Classifier: License :: OSI Approved :: GNU Affero General Public License v3
